.gitignore
CMakeLists.txt
LICENSE
README.md
pyproject.toml
setup.cfg
setup.py
asi_libs/armv7/libASICamera2.a
asi_libs/x64/libASICamera2.a
camera_zwo_asi/__init__.py
camera_zwo_asi/camera.py
camera_zwo_asi/image.py
camera_zwo_asi/main.py
camera_zwo_asi/py.typed
camera_zwo_asi/roi.py
camera_zwo_asi/version.py
camera_zwo_asi.egg-info/PKG-INFO
camera_zwo_asi.egg-info/SOURCES.txt
camera_zwo_asi.egg-info/dependency_links.txt
camera_zwo_asi.egg-info/entry_points.txt
camera_zwo_asi.egg-info/not-zip-safe
camera_zwo_asi.egg-info/requires.txt
camera_zwo_asi.egg-info/top_level.txt
cmake/FindUSB.cmake
include/ASICamera2.h
include/zwo_asi/bayer_pattern.hpp
include/zwo_asi/camera.hpp
include/zwo_asi/camera_attributes.hpp
include/zwo_asi/camera_exception.hpp
include/zwo_asi/camera_info.hpp
include/zwo_asi/camera_mode.hpp
include/zwo_asi/controllable.hpp
include/zwo_asi/controllable_exception.hpp
include/zwo_asi/guide_direction.hpp
include/zwo_asi/image_type.hpp
include/zwo_asi/roi.hpp
include/zwo_asi/roi_exception.hpp
include/zwo_asi/utils.hpp
src/bayer_pattern.cpp
src/camera.cpp
src/camera_exception.cpp
src/camera_info.cpp
src/camera_mode.cpp
src/controllable.cpp
src/controllable_exception.cpp
src/guide_direction.cpp
src/image_type.cpp
src/print.cpp
src/roi.cpp
src/roi_exception.cpp
src/utils.cpp
srcpy/bindings.cpp
tests/test.py