Metadata-Version: 2.1
Name: camera-zwo-asi
Version: 1.0.4
Summary: python wrapper for ZWO astronomical cameras
Home-page: https://github.com/MPI-IS/camera_zwo_asi
Author: Vincent Berenz
Author-email: vberenz@tue.mpg.de
License: BSD 3-Clause License
Platform: linux
Requires-Python: >=3.6
Provides-Extra: all
Provides-Extra: test
